lib/__init__.py
lib/EDALIB/__init__.py
lib/EDALIB/core.py
visulaizerlib-0.1.0.dist-info/licenses/LICENSE
visulaizerlib-0.1.0.dist-info/METADATA
visulaizerlib-0.1.0.dist-info/WHEEL
visulaizerlib-0.1.0.dist-info/top_level.txt
visulaizerlib-0.1.0.dist-info/RECORD
