Metadata-Version: 2.4
Name: visulaizerlib
Version: 0.1.0
Summary: A EDA package
Author: vishnu
Author-email: vishnu <vishnurrajeev@gmail.com>
License: MIT
Requires-Python: >=3.7
License-File: LICENSE
Dynamic: author
Dynamic: license-file
